generatr/__init__.py
generatr/__main__.py
generatr/generatr.py
generatr/dtdvalidate/__init__.py
generatr/dtdvalidate/example_input.xml
generatr/dtdvalidate/validation.py
generatr/dtdvalidate/xml_rules.dtd
generatr-0.252.dist-info/DESCRIPTION.rst
generatr-0.252.dist-info/METADATA
generatr-0.252.dist-info/RECORD
generatr-0.252.dist-info/WHEEL
generatr-0.252.dist-info/entry_points.txt
generatr-0.252.dist-info/metadata.json
generatr-0.252.dist-info/top_level.txt
