Metadata-Version: 2.0
Name: generatr
Version: 0.252
Summary: Dynamic multi-loci/mutli-repeat tract microsatellite sequence generator.
Home-page: https://github.com/helloabunai/RefGeneratr
Author: Alastair Maxwell/University of Glasgow
Author-email: alastair.maxwell@glasgow.ac.uk
License: GPLv3
Keywords: XML FASTA Genetic-references Bioinformatics Dat-analysis
Platform: UNKNOWN
Requires-Dist: lxml
